[
  {
    "name": "Image Card",
    "image": "./img/bg1.jpg"
  },
  {
    "name": "Image Card",
    "image":  "./img/bg2.jpg"
  },
  {
    "name": "Image Card",
    "image": "./img/bg3.jpg"
  },
  {
    "name": "Image Card",
    "image":  "./img/bg4.jpg"
  },
  {
    "name": "Image Card",
    "image": "./img/bg5.jpg"
  },
  {
    "name": "Image Card",
    "image":  "./img/bg6.jpg"
  },
  {
    "name": "Image Card",
    "image": "./img/bg7.jpg"
  },
  {
    "name": "Image Card",
    "image":  "./img/bg8.jpg"
  },
  {
    "name": "Image Card",
    "image": "./img/bg9.jpg"
  },
  {
    "name": "Image Card",
    "image":  "./img/bg10.jpg"
  },
  {
    "name": "Image Card",
    "image":  "./img/bg11.jpg"
  },
  {
    "name": "Image Card",
    "image":  "./img/bg12.jpg"
  }
]